[
    {
        "key": "group_626317ab13524",
        "title": "About",
        "fields": [
            {
                "key": "field_626317c135ba4",
                "label": "Studio description",
                "name": "studio_description",
                "type": "wysiwyg",
                "instructions": "",
                "required": 0,
                "conditional_logic": 0,
                "wrapper": {
                    "width": "",
                    "class": "",
                    "id": ""
                },
                "default_value": "",
                "tabs": "all",
                "toolbar": "basic",
                "media_upload": 0,
                "delay": 0
            },
            {
                "key": "field_6263182335ba6",
                "label": "Poetic Research title",
                "name": "poetic_research_title",
                "type": "text",
                "instructions": "",
                "required": 0,
                "conditional_logic": 0,
                "wrapper": {
                    "width": "",
                    "class": "",
                    "id": ""
                },
                "default_value": "Poetic Research",
                "placeholder": "",
                "prepend": "",
                "append": "",
                "maxlength": ""
            },
            {
                "key": "field_626317fb35ba5",
                "label": "Poetic Research description",
                "name": "poetic_research_description",
                "type": "wysiwyg",
                "instructions": "",
                "required": 0,
                "conditional_logic": 0,
                "wrapper": {
                    "width": "",
                    "class": "",
                    "id": ""
                },
                "default_value": "",
                "tabs": "all",
                "toolbar": "basic",
                "media_upload": 0,
                "delay": 0
            },
            {
                "key": "field_626318c635ba9",
                "label": "Location 1",
                "name": "location_1",
                "type": "wysiwyg",
                "instructions": "",
                "required": 0,
                "conditional_logic": 0,
                "wrapper": {
                    "width": "",
                    "class": "",
                    "id": ""
                },
                "default_value": "",
                "tabs": "all",
                "toolbar": "basic",
                "media_upload": 0,
                "delay": 0
            },
            {
                "key": "field_626318e435baa",
                "label": "Location 2",
                "name": "location_2",
                "type": "wysiwyg",
                "instructions": "",
                "required": 0,
                "conditional_logic": 0,
                "wrapper": {
                    "width": "",
                    "class": "",
                    "id": ""
                },
                "default_value": "",
                "tabs": "all",
                "toolbar": "basic",
                "media_upload": 0,
                "delay": 0
            },
            {
                "key": "field_626318eb35bab",
                "label": "Telephone",
                "name": "telephone",
                "type": "text",
                "instructions": "",
                "required": 0,
                "conditional_logic": 0,
                "wrapper": {
                    "width": "",
                    "class": "",
                    "id": ""
                },
                "default_value": "",
                "placeholder": "",
                "prepend": "",
                "append": "",
                "maxlength": ""
            },
            {
                "key": "field_6263190435bac",
                "label": "Email",
                "name": "email",
                "type": "email",
                "instructions": "",
                "required": 0,
                "conditional_logic": 0,
                "wrapper": {
                    "width": "",
                    "class": "",
                    "id": ""
                },
                "default_value": "",
                "placeholder": "",
                "prepend": "",
                "append": ""
            },
            {
                "key": "field_6263191a35bad",
                "label": "People",
                "name": "people",
                "type": "relationship",
                "instructions": "",
                "required": 0,
                "conditional_logic": 0,
                "wrapper": {
                    "width": "",
                    "class": "",
                    "id": ""
                },
                "post_type": [
                    "person"
                ],
                "taxonomy": "",
                "filters": [
                    "search",
                    "post_type",
                    "taxonomy"
                ],
                "elements": "",
                "min": "",
                "max": "",
                "return_format": "object",
                "acfe_bidirectional": {
                    "acfe_bidirectional_enabled": "0"
                }
            }
        ],
        "location": [
            [
                {
                    "param": "page",
                    "operator": "==",
                    "value": "29"
                }
            ]
        ],
        "menu_order": 0,
        "position": "normal",
        "style": "seamless",
        "label_placement": "top",
        "instruction_placement": "label",
        "hide_on_screen": [
            "the_content",
            "discussion",
            "comments"
        ],
        "active": true,
        "description": "",
        "show_in_rest": 0,
        "acfe_display_title": "",
        "acfe_autosync": "",
        "acfe_form": 0,
        "acfe_meta": "",
        "acfe_note": ""
    },
    {
        "key": "group_625f0e8049821",
        "title": "Footer",
        "fields": [
            {
                "key": "field_625f0e9f1865d",
                "label": "Copyright",
                "name": "copyright",
                "type": "text",
                "instructions": "",
                "required": 0,
                "conditional_logic": 0,
                "wrapper": {
                    "width": "",
                    "class": "",
                    "id": ""
                },
                "default_value": "",
                "placeholder": "",
                "prepend": "",
                "append": "",
                "maxlength": ""
            },
            {
                "key": "field_625f0eb71865e",
                "label": "Additional info",
                "name": "additional_info",
                "type": "text",
                "instructions": "",
                "required": 0,
                "conditional_logic": 0,
                "wrapper": {
                    "width": "",
                    "class": "",
                    "id": ""
                },
                "default_value": "",
                "placeholder": "",
                "prepend": "",
                "append": "",
                "maxlength": ""
            },
            {
                "key": "field_625f0ef11865f",
                "label": "Links",
                "name": "links",
                "type": "repeater",
                "instructions": "",
                "required": 0,
                "conditional_logic": 0,
                "wrapper": {
                    "width": "",
                    "class": "",
                    "id": ""
                },
                "acfe_repeater_stylised_button": 0,
                "collapsed": "",
                "min": 0,
                "max": 0,
                "layout": "table",
                "button_label": "Add link",
                "sub_fields": [
                    {
                        "key": "field_625f0f0618660",
                        "label": "Link",
                        "name": "link",
                        "type": "link",
                        "instructions": "",
                        "required": 0,
                        "conditional_logic": 0,
                        "wrapper": {
                            "width": "",
                            "class": "",
                            "id": ""
                        },
                        "return_format": "array"
                    }
                ]
            }
        ],
        "location": [
            [
                {
                    "param": "options_page",
                    "operator": "==",
                    "value": "footer"
                }
            ]
        ],
        "menu_order": 0,
        "position": "normal",
        "style": "seamless",
        "label_placement": "top",
        "instruction_placement": "label",
        "hide_on_screen": [
            "the_content"
        ],
        "active": true,
        "description": "",
        "show_in_rest": 0,
        "acfe_display_title": "",
        "acfe_autosync": "",
        "acfe_form": 0,
        "acfe_meta": "",
        "acfe_note": ""
    },
    {
        "key": "group_6262c2e9dfd30",
        "title": "Home",
        "fields": [
            {
                "key": "field_6262c5459a126",
                "label": "Adding Projects and Learning Opportunities",
                "name": "",
                "type": "message",
                "instructions": "",
                "required": 0,
                "conditional_logic": 0,
                "wrapper": {
                    "width": "",
                    "class": "",
                    "id": ""
                },
                "message": "These will auto-populate in this page from the <a href=\"\/wp-admin\/edit.php?post_type=project\">Projects menu<\/a> and the <a href=\"\/wp-admin\/edit.php?post_type=learning-opportunity\">Learning Opportunities<\/a> in the sidebar. To add new items you can do so within those sections of the backend.\r\n\r\nThe order of the items on the front-end will be randomized, while the size of the item can be selected when editing the specific item.",
                "new_lines": "wpautop",
                "esc_html": 0
            },
            {
                "key": "field_628684170c082",
                "label": "Projects and Learning Opportunities",
                "name": "projects_and_learning_opportunities",
                "type": "relationship",
                "instructions": "",
                "required": 0,
                "conditional_logic": 0,
                "wrapper": {
                    "width": "",
                    "class": "",
                    "id": ""
                },
                "post_type": [
                    "project",
                    "learning-opportunity"
                ],
                "taxonomy": "",
                "filters": [
                    "search",
                    "post_type",
                    "taxonomy"
                ],
                "elements": "",
                "min": "",
                "max": "",
                "return_format": "object",
                "acfe_bidirectional": {
                    "acfe_bidirectional_enabled": "0"
                }
            }
        ],
        "location": [
            [
                {
                    "param": "page",
                    "operator": "==",
                    "value": "23"
                }
            ]
        ],
        "menu_order": 0,
        "position": "normal",
        "style": "seamless",
        "label_placement": "top",
        "instruction_placement": "label",
        "hide_on_screen": [
            "the_content",
            "discussion",
            "comments",
            "page_attributes",
            "featured_image"
        ],
        "active": true,
        "description": "",
        "show_in_rest": 0,
        "acfe_display_title": "",
        "acfe_autosync": "",
        "acfe_form": 0,
        "acfe_meta": "",
        "acfe_note": ""
    },
    {
        "key": "group_625f11362e667",
        "title": "Learning opportunity",
        "fields": [
            {
                "key": "field_628cfa3216f99",
                "label": "Custom anchor",
                "name": "custom_anchor",
                "type": "acfe_slug",
                "instructions": "Feel free to enter text either with spaces or hyphens. This field will automatically remove spaces etc, so something like \"My Custom Anchor\" would be converted to \"my-custom-anchor\".",
                "required": 1,
                "conditional_logic": 0,
                "wrapper": {
                    "width": "",
                    "class": "",
                    "id": ""
                },
                "default_value": "",
                "placeholder": "",
                "prepend": "",
                "append": "",
                "maxlength": ""
            },
            {
                "key": "field_6262c8453ee11",
                "label": "Homepage size",
                "name": "homepage_size",
                "type": "button_group",
                "instructions": "",
                "required": 0,
                "conditional_logic": 0,
                "wrapper": {
                    "width": "",
                    "class": "",
                    "id": ""
                },
                "choices": {
                    "Small": "Small",
                    "Large": "Large"
                },
                "allow_null": 0,
                "default_value": "Small",
                "layout": "horizontal",
                "return_format": "value"
            },
            {
                "key": "field_625f114e8a87a",
                "label": "Thumbnail image",
                "name": "thumbnail_image",
                "type": "image",
                "instructions": "This will be used on the homepage.",
                "required": 0,
                "conditional_logic": 0,
                "wrapper": {
                    "width": "",
                    "class": "",
                    "id": ""
                },
                "uploader": "",
                "acfe_thumbnail": 1,
                "return_format": "array",
                "preview_size": "medium",
                "min_width": "",
                "min_height": "",
                "min_size": "",
                "max_width": "",
                "max_height": "",
                "max_size": "",
                "mime_types": "",
                "library": "all"
            },
            {
                "key": "field_628cf0cde4c5b",
                "label": "Embed",
                "name": "embed",
                "type": "oembed",
                "instructions": "This will only appear on the Learning Opportunities page. If no Embed is added, the Thumbnail Image will be used instead.",
                "required": 0,
                "conditional_logic": 0,
                "wrapper": {
                    "width": "",
                    "class": "",
                    "id": ""
                },
                "width": "",
                "height": ""
            },
            {
                "key": "field_625f11438a879",
                "label": "Subtitle",
                "name": "subtitle",
                "type": "text",
                "instructions": "",
                "required": 0,
                "conditional_logic": 0,
                "wrapper": {
                    "width": "",
                    "class": "",
                    "id": ""
                },
                "default_value": "",
                "placeholder": "",
                "prepend": "",
                "append": "",
                "maxlength": ""
            },
            {
                "key": "field_625f115d8a87b",
                "label": "Description",
                "name": "description",
                "type": "wysiwyg",
                "instructions": "",
                "required": 0,
                "conditional_logic": 0,
                "wrapper": {
                    "width": "",
                    "class": "",
                    "id": ""
                },
                "default_value": "",
                "tabs": "all",
                "toolbar": "basic",
                "media_upload": 0,
                "delay": 0
            },
            {
                "key": "field_625f116e8a87c",
                "label": "Links",
                "name": "links",
                "type": "repeater",
                "instructions": "",
                "required": 0,
                "conditional_logic": 0,
                "wrapper": {
                    "width": "",
                    "class": "",
                    "id": ""
                },
                "acfe_repeater_stylised_button": 0,
                "collapsed": "",
                "min": 0,
                "max": 0,
                "layout": "table",
                "button_label": "Add Link",
                "sub_fields": [
                    {
                        "key": "field_6261c8ab3a477",
                        "label": "Link",
                        "name": "link",
                        "type": "link",
                        "instructions": "",
                        "required": 0,
                        "conditional_logic": 0,
                        "wrapper": {
                            "width": "",
                            "class": "",
                            "id": ""
                        },
                        "return_format": "array"
                    }
                ]
            },
            {
                "key": "field_625f11848a87d",
                "label": "Type of opportunity",
                "name": "type_of_opportunity",
                "type": "acfe_taxonomy_terms",
                "instructions": "",
                "required": 0,
                "conditional_logic": 0,
                "wrapper": {
                    "width": "",
                    "class": "",
                    "id": ""
                },
                "taxonomy": [
                    "opportunity-type"
                ],
                "allow_terms": "",
                "allow_level": "",
                "field_type": "checkbox",
                "default_value": [],
                "return_format": "object",
                "layout": "vertical",
                "toggle": 0,
                "save_terms": 0,
                "load_terms": 0,
                "choices": [],
                "ui": 0,
                "multiple": 0,
                "allow_null": 0,
                "ajax": 0,
                "placeholder": "",
                "search_placeholder": "",
                "allow_custom": 0,
                "other_choice": 0
            }
        ],
        "location": [
            [
                {
                    "param": "post_type",
                    "operator": "==",
                    "value": "learning-opportunity"
                }
            ]
        ],
        "menu_order": 0,
        "position": "normal",
        "style": "seamless",
        "label_placement": "top",
        "instruction_placement": "label",
        "hide_on_screen": [
            "the_content",
            "discussion",
            "comments"
        ],
        "active": true,
        "description": "",
        "show_in_rest": 0,
        "acfe_display_title": "",
        "acfe_autosync": "",
        "acfe_form": 0,
        "acfe_meta": "",
        "acfe_note": ""
    },
    {
        "key": "group_62631a138aae1",
        "title": "Person",
        "fields": [
            {
                "key": "field_62631a28d04e4",
                "label": "Title",
                "name": "job_title",
                "type": "text",
                "instructions": "",
                "required": 0,
                "conditional_logic": 0,
                "wrapper": {
                    "width": "",
                    "class": "",
                    "id": ""
                },
                "default_value": "",
                "placeholder": "",
                "prepend": "",
                "append": "",
                "maxlength": ""
            },
            {
                "key": "field_62631a3bd04e5",
                "label": "Headshot",
                "name": "headshot",
                "type": "image",
                "instructions": "",
                "required": 0,
                "conditional_logic": 0,
                "wrapper": {
                    "width": "",
                    "class": "",
                    "id": ""
                },
                "uploader": "",
                "acfe_thumbnail": 1,
                "return_format": "array",
                "preview_size": "medium",
                "min_width": "",
                "min_height": "",
                "min_size": "",
                "max_width": "",
                "max_height": "",
                "max_size": "",
                "mime_types": "",
                "library": "all"
            },
            {
                "key": "field_62631a56d04e6",
                "label": "Image size",
                "name": "image_size",
                "type": "button_group",
                "instructions": "",
                "required": 0,
                "conditional_logic": 0,
                "wrapper": {
                    "width": "",
                    "class": "",
                    "id": ""
                },
                "choices": {
                    "Small": "Small",
                    "Large": "Large"
                },
                "allow_null": 0,
                "default_value": "Small",
                "layout": "horizontal",
                "return_format": "value"
            },
            {
                "key": "field_62631a7cd04e7",
                "label": "Bio",
                "name": "bio",
                "type": "wysiwyg",
                "instructions": "",
                "required": 0,
                "conditional_logic": 0,
                "wrapper": {
                    "width": "",
                    "class": "",
                    "id": ""
                },
                "default_value": "",
                "tabs": "all",
                "toolbar": "basic",
                "media_upload": 0,
                "delay": 0
            }
        ],
        "location": [
            [
                {
                    "param": "post_type",
                    "operator": "==",
                    "value": "person"
                }
            ]
        ],
        "menu_order": 0,
        "position": "normal",
        "style": "seamless",
        "label_placement": "top",
        "instruction_placement": "label",
        "hide_on_screen": [
            "the_content",
            "discussion",
            "comments"
        ],
        "active": true,
        "description": "",
        "show_in_rest": 0,
        "acfe_display_title": "",
        "acfe_autosync": "",
        "acfe_form": 0,
        "acfe_meta": "",
        "acfe_note": ""
    },
    {
        "key": "group_625deb9a0a926",
        "title": "Play",
        "fields": [
            {
                "key": "field_625deba4a1071",
                "label": "HTML",
                "name": "html",
                "type": "acfe_code_editor",
                "instructions": "",
                "required": 0,
                "conditional_logic": 0,
                "wrapper": {
                    "width": "",
                    "class": "",
                    "id": ""
                },
                "default_value": "",
                "placeholder": "",
                "mode": "text\/html",
                "lines": 1,
                "indent_unit": 4,
                "maxlength": "",
                "rows": 10,
                "max_rows": "",
                "return_entities": 0
            },
            {
                "key": "field_625dec1ea1072",
                "label": "CSS",
                "name": "css",
                "type": "acfe_code_editor",
                "instructions": "",
                "required": 0,
                "conditional_logic": 0,
                "wrapper": {
                    "width": "",
                    "class": "",
                    "id": ""
                },
                "default_value": "",
                "placeholder": "",
                "mode": "css",
                "lines": 1,
                "indent_unit": 4,
                "maxlength": "",
                "rows": 10,
                "max_rows": "",
                "return_entities": 0
            },
            {
                "key": "field_625dec32a1073",
                "label": "JavaScript",
                "name": "javascript",
                "type": "acfe_code_editor",
                "instructions": "",
                "required": 0,
                "conditional_logic": 0,
                "wrapper": {
                    "width": "",
                    "class": "",
                    "id": ""
                },
                "default_value": "",
                "placeholder": "",
                "mode": "javascript",
                "lines": 1,
                "indent_unit": 4,
                "maxlength": "",
                "rows": 10,
                "max_rows": "",
                "return_entities": 0
            }
        ],
        "location": [
            [
                {
                    "param": "page",
                    "operator": "==",
                    "value": "25"
                }
            ]
        ],
        "menu_order": 0,
        "position": "normal",
        "style": "seamless",
        "label_placement": "top",
        "instruction_placement": "label",
        "hide_on_screen": [
            "the_content",
            "discussion",
            "comments"
        ],
        "active": true,
        "description": "",
        "show_in_rest": 1,
        "acfe_display_title": "",
        "acfe_autosync": "",
        "acfe_form": 0,
        "acfe_meta": "",
        "acfe_note": ""
    },
    {
        "key": "group_625ddaa0876ed",
        "title": "Project",
        "fields": [
            {
                "key": "field_6262d9ff2132a",
                "label": "Project settings",
                "name": "",
                "type": "accordion",
                "instructions": "",
                "required": 0,
                "conditional_logic": 0,
                "wrapper": {
                    "width": "",
                    "class": "",
                    "id": ""
                },
                "open": 0,
                "multi_expand": 0,
                "endpoint": 0
            },
            {
                "key": "field_6262c89665596",
                "label": "Homepage size",
                "name": "homepage_size",
                "type": "button_group",
                "instructions": "",
                "required": 0,
                "conditional_logic": 0,
                "wrapper": {
                    "width": "",
                    "class": "",
                    "id": ""
                },
                "choices": {
                    "Small": "Small",
                    "Large": "Large"
                },
                "allow_null": 0,
                "default_value": "Small",
                "layout": "horizontal",
                "return_format": "value"
            },
            {
                "key": "field_6262d9a821328",
                "label": "Thumbnail Image",
                "name": "thumbnail_image",
                "type": "image",
                "instructions": "",
                "required": 0,
                "conditional_logic": 0,
                "wrapper": {
                    "width": "",
                    "class": "",
                    "id": ""
                },
                "uploader": "",
                "acfe_thumbnail": 1,
                "return_format": "array",
                "preview_size": "medium",
                "min_width": "",
                "min_height": "",
                "min_size": "",
                "max_width": "",
                "max_height": "",
                "max_size": "",
                "mime_types": "",
                "library": "all"
            },
            {
                "key": "field_6262d9ed21329",
                "label": "Project details",
                "name": "",
                "type": "accordion",
                "instructions": "",
                "required": 0,
                "conditional_logic": 0,
                "wrapper": {
                    "width": "",
                    "class": "",
                    "id": ""
                },
                "open": 0,
                "multi_expand": 0,
                "endpoint": 0
            },
            {
                "key": "field_6261c5d43a34e",
                "label": "Subtitle",
                "name": "subtitle",
                "type": "text",
                "instructions": "",
                "required": 0,
                "conditional_logic": 0,
                "wrapper": {
                    "width": "",
                    "class": "",
                    "id": ""
                },
                "default_value": "",
                "placeholder": "",
                "prepend": "",
                "append": "",
                "maxlength": ""
            },
            {
                "key": "field_625ddac5dc9f2",
                "label": "Project description",
                "name": "project_description",
                "type": "wysiwyg",
                "instructions": "",
                "required": 0,
                "conditional_logic": 0,
                "wrapper": {
                    "width": "",
                    "class": "",
                    "id": ""
                },
                "default_value": "",
                "tabs": "all",
                "toolbar": "basic",
                "media_upload": 0,
                "delay": 0
            },
            {
                "key": "field_625ddbfddc9f6",
                "label": "Deliverables",
                "name": "deliverables",
                "type": "flexible_content",
                "instructions": "",
                "required": 0,
                "conditional_logic": 0,
                "wrapper": {
                    "width": "",
                    "class": "",
                    "id": ""
                },
                "layouts": {
                    "layout_625ddc0ab9e79": {
                        "key": "layout_625ddc0ab9e79",
                        "name": "deliverable",
                        "label": "Deliverable",
                        "display": "row",
                        "sub_fields": [
                            {
                                "key": "field_62616f01af42b",
                                "label": "Type",
                                "name": "type",
                                "type": "acfe_taxonomy_terms",
                                "instructions": "",
                                "required": 0,
                                "conditional_logic": 0,
                                "wrapper": {
                                    "width": "",
                                    "class": "",
                                    "id": ""
                                },
                                "taxonomy": [
                                    "deliverable-type"
                                ],
                                "allow_terms": "",
                                "allow_level": "",
                                "field_type": "select",
                                "default_value": [],
                                "return_format": "object",
                                "ui": 0,
                                "allow_null": 0,
                                "multiple": 0,
                                "save_terms": 0,
                                "load_terms": 0,
                                "choices": [],
                                "ajax": 0,
                                "placeholder": "",
                                "search_placeholder": "",
                                "layout": "",
                                "toggle": 0,
                                "allow_custom": 0,
                                "other_choice": 0
                            },
                            {
                                "key": "field_625de292dc9f8",
                                "label": "Deliverable details",
                                "name": "deliverable_details",
                                "type": "wysiwyg",
                                "instructions": "",
                                "required": 0,
                                "conditional_logic": 0,
                                "wrapper": {
                                    "width": "",
                                    "class": "",
                                    "id": ""
                                },
                                "default_value": "",
                                "tabs": "all",
                                "toolbar": "basic",
                                "media_upload": 0,
                                "delay": 0
                            },
                            {
                                "key": "field_625f171e04908",
                                "label": "Carousel",
                                "name": "carousel",
                                "type": "repeater",
                                "instructions": "",
                                "required": 0,
                                "conditional_logic": 0,
                                "wrapper": {
                                    "width": "",
                                    "class": "",
                                    "id": ""
                                },
                                "acfe_repeater_stylised_button": 0,
                                "collapsed": "",
                                "min": 0,
                                "max": 0,
                                "layout": "table",
                                "button_label": "Add Media",
                                "sub_fields": [
                                    {
                                        "key": "field_625f174c04909",
                                        "label": "Image or Video?",
                                        "name": "image_or_video",
                                        "type": "button_group",
                                        "instructions": "",
                                        "required": 0,
                                        "conditional_logic": 0,
                                        "wrapper": {
                                            "width": "",
                                            "class": "",
                                            "id": ""
                                        },
                                        "choices": {
                                            "Image": "Image",
                                            "Video": "Video"
                                        },
                                        "allow_null": 0,
                                        "default_value": "",
                                        "layout": "horizontal",
                                        "return_format": "value"
                                    },
                                    {
                                        "key": "field_625f17760490a",
                                        "label": "Image",
                                        "name": "image",
                                        "type": "image",
                                        "instructions": "",
                                        "required": 0,
                                        "conditional_logic": [
                                            [
                                                {
                                                    "field": "field_625f174c04909",
                                                    "operator": "==",
                                                    "value": "Image"
                                                }
                                            ]
                                        ],
                                        "wrapper": {
                                            "width": "",
                                            "class": "",
                                            "id": ""
                                        },
                                        "uploader": "",
                                        "acfe_thumbnail": 0,
                                        "return_format": "array",
                                        "preview_size": "medium",
                                        "min_width": "",
                                        "min_height": "",
                                        "min_size": "",
                                        "max_width": "",
                                        "max_height": "",
                                        "max_size": "",
                                        "mime_types": "",
                                        "library": "all"
                                    },
                                    {
                                        "key": "field_625f17a80490b",
                                        "label": "Video",
                                        "name": "video",
                                        "type": "oembed",
                                        "instructions": "",
                                        "required": 0,
                                        "conditional_logic": [
                                            [
                                                {
                                                    "field": "field_625f174c04909",
                                                    "operator": "==",
                                                    "value": "Video"
                                                }
                                            ]
                                        ],
                                        "wrapper": {
                                            "width": "",
                                            "class": "",
                                            "id": ""
                                        },
                                        "width": "",
                                        "height": ""
                                    }
                                ]
                            }
                        ],
                        "min": "",
                        "max": "",
                        "acfe_flexible_render_template": false,
                        "acfe_flexible_render_style": false,
                        "acfe_flexible_render_script": false,
                        "acfe_flexible_thumbnail": false,
                        "acfe_flexible_settings": false,
                        "acfe_flexible_settings_size": "medium",
                        "acfe_flexible_modal_edit_size": false,
                        "acfe_flexible_category": false
                    }
                },
                "button_label": "Add Deliverable",
                "min": "",
                "max": "",
                "acfe_flexible_advanced": false,
                "acfe_flexible_stylised_button": false,
                "acfe_flexible_hide_empty_message": false,
                "acfe_flexible_empty_message": "",
                "acfe_flexible_layouts_templates": false,
                "acfe_flexible_layouts_previews": false,
                "acfe_flexible_layouts_placeholder": false,
                "acfe_flexible_layouts_thumbnails": false,
                "acfe_flexible_layouts_settings": false,
                "acfe_flexible_async": [],
                "acfe_flexible_add_actions": [],
                "acfe_flexible_remove_button": [],
                "acfe_flexible_layouts_state": false,
                "acfe_flexible_modal_edit": {
                    "acfe_flexible_modal_edit_enabled": false,
                    "acfe_flexible_modal_edit_size": "large"
                },
                "acfe_flexible_modal": {
                    "acfe_flexible_modal_enabled": false,
                    "acfe_flexible_modal_title": false,
                    "acfe_flexible_modal_size": "full",
                    "acfe_flexible_modal_col": "4",
                    "acfe_flexible_modal_categories": false
                }
            },
            {
                "key": "field_625de8e93501d",
                "label": "Poetic Research",
                "name": "",
                "type": "accordion",
                "instructions": "",
                "required": 0,
                "conditional_logic": 0,
                "wrapper": {
                    "width": "",
                    "class": "",
                    "id": ""
                },
                "open": 0,
                "multi_expand": 0,
                "endpoint": 0
            },
            {
                "key": "field_625ddbdbdc9f5",
                "label": "General Title",
                "name": "poetic_research_title",
                "type": "text",
                "instructions": "",
                "required": 0,
                "conditional_logic": 0,
                "wrapper": {
                    "width": "",
                    "class": "",
                    "id": ""
                },
                "default_value": "Poetic Research",
                "placeholder": "",
                "prepend": "",
                "append": "",
                "maxlength": ""
            },
            {
                "key": "field_627ec0a63a428",
                "label": "Project Specific Title",
                "name": "project_specific_title",
                "type": "text",
                "instructions": "",
                "required": 0,
                "conditional_logic": 0,
                "wrapper": {
                    "width": "",
                    "class": "",
                    "id": ""
                },
                "default_value": "",
                "placeholder": "",
                "prepend": "",
                "append": "",
                "maxlength": ""
            },
            {
                "key": "field_625ddb39dc9f3",
                "label": "Description",
                "name": "poetic_research_description",
                "type": "wysiwyg",
                "instructions": "",
                "required": 0,
                "conditional_logic": 0,
                "wrapper": {
                    "width": "",
                    "class": "",
                    "id": ""
                },
                "default_value": "",
                "tabs": "all",
                "toolbar": "basic",
                "media_upload": 0,
                "delay": 0
            },
            {
                "key": "field_625f18d6fdc4f",
                "label": "Carousel",
                "name": "carousel",
                "type": "repeater",
                "instructions": "",
                "required": 0,
                "conditional_logic": 0,
                "wrapper": {
                    "width": "",
                    "class": "",
                    "id": ""
                },
                "acfe_repeater_stylised_button": 0,
                "collapsed": "",
                "min": 0,
                "max": 0,
                "layout": "table",
                "button_label": "Add Media",
                "sub_fields": [
                    {
                        "key": "field_625f18d6fdc50",
                        "label": "Image or Video?",
                        "name": "image_or_video",
                        "type": "button_group",
                        "instructions": "",
                        "required": 0,
                        "conditional_logic": 0,
                        "wrapper": {
                            "width": "",
                            "class": "",
                            "id": ""
                        },
                        "choices": {
                            "Image": "Image",
                            "Video": "Video"
                        },
                        "allow_null": 0,
                        "default_value": "",
                        "layout": "horizontal",
                        "return_format": "value"
                    },
                    {
                        "key": "field_625f18d6fdc51",
                        "label": "Image",
                        "name": "image",
                        "type": "image",
                        "instructions": "",
                        "required": 0,
                        "conditional_logic": [
                            [
                                {
                                    "field": "field_625f18d6fdc50",
                                    "operator": "==",
                                    "value": "Image"
                                }
                            ]
                        ],
                        "wrapper": {
                            "width": "",
                            "class": "",
                            "id": ""
                        },
                        "uploader": "",
                        "acfe_thumbnail": 0,
                        "return_format": "array",
                        "preview_size": "medium",
                        "library": "all",
                        "min_width": "",
                        "min_height": "",
                        "min_size": "",
                        "max_width": "",
                        "max_height": "",
                        "max_size": "",
                        "mime_types": ""
                    },
                    {
                        "key": "field_625f18d6fdc52",
                        "label": "Video",
                        "name": "video",
                        "type": "oembed",
                        "instructions": "",
                        "required": 0,
                        "conditional_logic": [
                            [
                                {
                                    "field": "field_625f18d6fdc50",
                                    "operator": "==",
                                    "value": "Video"
                                }
                            ]
                        ],
                        "wrapper": {
                            "width": "",
                            "class": "",
                            "id": ""
                        },
                        "width": "",
                        "height": ""
                    },
                    {
                        "key": "field_6283ec1da13ea",
                        "label": "Caption",
                        "name": "caption",
                        "type": "text",
                        "instructions": "",
                        "required": 0,
                        "conditional_logic": 0,
                        "wrapper": {
                            "width": "",
                            "class": "",
                            "id": ""
                        },
                        "default_value": "",
                        "placeholder": "",
                        "prepend": "",
                        "append": "",
                        "maxlength": ""
                    }
                ]
            }
        ],
        "location": [
            [
                {
                    "param": "post_type",
                    "operator": "==",
                    "value": "project"
                }
            ]
        ],
        "menu_order": 0,
        "position": "normal",
        "style": "seamless",
        "label_placement": "top",
        "instruction_placement": "label",
        "hide_on_screen": [
            "the_content",
            "discussion",
            "comments"
        ],
        "active": true,
        "description": "",
        "show_in_rest": 1,
        "acfe_display_title": "",
        "acfe_autosync": "",
        "acfe_form": 0,
        "acfe_meta": "",
        "acfe_note": ""
    },
    {
        "key": "group_625dec974ada3",
        "title": "Teaching",
        "fields": [
            {
                "key": "field_625decb163b42",
                "label": "Short description",
                "name": "short_description",
                "type": "wysiwyg",
                "instructions": "",
                "required": 0,
                "conditional_logic": 0,
                "wrapper": {
                    "width": "",
                    "class": "",
                    "id": ""
                },
                "default_value": "",
                "tabs": "all",
                "toolbar": "basic",
                "media_upload": 0,
                "delay": 0
            },
            {
                "key": "field_625decc463b43",
                "label": "Long description",
                "name": "long_description",
                "type": "wysiwyg",
                "instructions": "",
                "required": 0,
                "conditional_logic": 0,
                "wrapper": {
                    "width": "",
                    "class": "",
                    "id": ""
                },
                "default_value": "",
                "tabs": "all",
                "toolbar": "basic",
                "media_upload": 0,
                "delay": 0
            },
            {
                "key": "field_625decde63b44",
                "label": "Learning opportunities",
                "name": "learning_opportunities",
                "type": "relationship",
                "instructions": "",
                "required": 0,
                "conditional_logic": 0,
                "wrapper": {
                    "width": "",
                    "class": "",
                    "id": ""
                },
                "post_type": [
                    "learning-opportunity"
                ],
                "taxonomy": "",
                "filters": [
                    "search",
                    "post_type",
                    "taxonomy"
                ],
                "elements": "",
                "min": "",
                "max": "",
                "return_format": "object",
                "acfe_bidirectional": {
                    "acfe_bidirectional_enabled": "0"
                }
            }
        ],
        "location": [
            [
                {
                    "param": "page",
                    "operator": "==",
                    "value": "27"
                }
            ]
        ],
        "menu_order": 0,
        "position": "normal",
        "style": "seamless",
        "label_placement": "top",
        "instruction_placement": "label",
        "hide_on_screen": [
            "the_content",
            "discussion",
            "comments"
        ],
        "active": true,
        "description": "",
        "show_in_rest": 0,
        "acfe_display_title": "",
        "acfe_autosync": "",
        "acfe_form": 0,
        "acfe_meta": "",
        "acfe_note": ""
    }
]